stormtrooper/__init__.py
stormtrooper/_setfit.py
stormtrooper/chat.py
stormtrooper/error.py
stormtrooper/generative.py
stormtrooper/openai.py
stormtrooper/set_fit.py
stormtrooper/text2text.py
stormtrooper/text_gen_inference.py
stormtrooper/trooper.py
stormtrooper/zero_shot.py
stormtrooper-1.0.1.dist-info/LICENSE
stormtrooper-1.0.1.dist-info/METADATA
stormtrooper-1.0.1.dist-info/WHEEL
stormtrooper-1.0.1.dist-info/RECORD
