Metadata-Version: 2.1
Name: stormtrooper
Version: 1.0.1
Summary: Transformer/LLM-based zero and few-shot classification in scikit-learn pipelines
License: MIT
Author: Márton Kardos
Author-email: power.up1163@gmail.com
Requires-Python: >=3.9,<4.0
Classifier: License :: OSI Approved :: MIT License
Classifier: Programming Language :: Python :: 3
Classifier: Programming Language :: Python :: 3.9
Classifier: Programming Language :: Python :: 3.10
Classifier: Programming Language :: Python :: 3.11
Classifier: Programming Language :: Python :: 3.12
Provides-Extra: docs
Requires-Dist: accelerate (>=0.2.1)
Requires-Dist: aiohttp (>=3.8.0,<4.0.0)
Requires-Dist: datasets (>=2.14.0)
Requires-Dist: mkdocs (>=1.5.2,<2.0.0) ; extra == "docs"
Requires-Dist: mkdocs-material (>=9.5.12,<10.0.0) ; extra == "docs"
Requires-Dist: mkdocstrings[python] (>=0.24.0,<0.25.0) ; extra == "docs"
Requires-Dist: numpy (>=1.23.0,<2.0.0)
Requires-Dist: openai (>=1.40.0)
Requires-Dist: scikit-learn (>=1.2.0,<2.0.0)
Requires-Dist: sentence-transformers (>=3.0.1)
Requires-Dist: thefuzz (>=0.18.0,<0.19.0)
Requires-Dist: torch (>=2.0.0)
Requires-Dist: tqdm (>=4.60.0,<5.0.0)
Requires-Dist: transformers (>=4.25.0,<4.41.0)
